{
  "type": "jiagureappear:character_assembling_non_mirrored",
  "category": "misc",
  "key": {
    "L": {
      "type": "jiagureappear:character_ingredient",
      "inscription": "貝"
    },
    "R": {
      "type": "jiagureappear:character_ingredient",
      "inscription": "猋"
    }
  },
  "pattern": [
    "   ",
    "LR ",
    "   "
  ],
  "result": {
    "components": {
      "minecraft:custom_data": {
        "inscription": "贆"
      }
    },
    "count": 1,
    "id": "jiagureappear:character"
  },
  "result_inscription": "贆"
}